Workbook

Sheet Bareme ADVENIR
A1: BAREME ADVENIR — Outre-mer (à actualiser sur advenir.mobi)
A3: Cas d'usage | B3: Code | C3: Aide max / point (€) | D3: Taux max (% HT) | E3: Plafond installation (€) | F3: Notes
A4: Residentiel collectif (parking copro/social) | B4: RES_COL | C4: 960 | D4: 0.5 | E4: 1920 | F4: Outre-mer : majoration possible de 10–20%. Verifier le bareme.
A5: Salaries — point individuel | B5: SAL_IND | C5: 960 | D5: 0.5 | E5: 1920 | F5: Borne dediee a un salarie identifie.
A6: Salaries — point partage | B6: SAL_PAR | C6: 600 | D6: 0.5 | E6: 1200 | F6: Plusieurs salaries se partagent la borne.
A7: Flotte/visiteurs entreprise | B7: FLT_ENT | C7: 1500 | D7: 0.5 | E7: 3000 | F7: Parking employeur ouvert visiteurs.
A8: Voirie publique — AC | B8: VOI_AC | C8: 2200 | D8: 0.3 | E8: 7330 | F8: Borne installee en voirie communale.
A9: Voirie publique — DC (rapide) | B9: VOI_DC | C9: 8100 | D9: 0.3 | E9: 27000 | F9: Charge rapide DC ≥ 50 kW.
A10: Parking ouvert public (prive ouvert) — AC | B10: POP_AC | C10: 1700 | D10: 0.2 | E10: 8500 | F10: Centre commercial, hotel, etc.
A11: Parking ouvert public — DC | B11: POP_DC | C11: 9000 | D11: 0.2 | E11: 45000 | F11: Charge rapide DC ≥ 50 kW.
A12: Poids lourds (PL) | B12: PL_DC | C12: 960000 | D12: 0.4 | E12: 2400000 | F12: Bornes haute puissance ≥ 150 kW.
A15: Note : ces montants sont indicatifs et issus du bareme outre-mer 2026.
A16: Verifier les valeurs en vigueur avant depot sur https://advenir.mobi

Sheet Chiffrage
A1: EGREENCITY'S — Chiffrage ADVENIR par site
A2: Editer les colonnes en BLEU. Les colonnes en NOIR sont calculees automatiquement.
A4: # | B4: Commune | C4: Site / Adresse | D4: Type de borne | E4: Cas d'usage (code) | F4: Nb points | G4: Cout HT / point (€) | H4: Cout HT total (€) | I4: Aide unitaire bareme (€) | J4: Taux max (% HT) | K4: Aide ADVENIR calculee (€) | L4: Reste a charge HT (€)
A5: 1 | B5: Cayenne | C5: Hotel de Ville — parking | D5: Totem 5 departs (110 kVa) | E5: VOI_AC | F5: 5 | G5: 11400 | H5: =F5*G5 | I5: =IFERROR(VLOOKUP(E5,'Bareme ADVENIR'!$B$4:$E$13,2,FALSE),0) | J5: =IFERROR(VLOOKUP(E5,'Bareme ADVENIR'!$B$4:$E$13,3,FALSE),0) | K5: =MIN(I5*F5,H5*J5) | L5: =H5-K5
A6: 2 | B6: Cayenne | C6: Marche central — voirie | D6: Totem 3 departs (36 kVa) | E6: VOI_AC | F6: 3 | G6: 7100 | H6: =F6*G6 | I6: =IFERROR(VLOOKUP(E6,'Bareme ADVENIR'!$B$4:$E$13,2,FALSE),0) | J6: =IFERROR(VLOOKUP(E6,'Bareme ADVENIR'!$B$4:$E$13,3,FALSE),0) | K6: =MIN(I6*F6,H6*J6) | L6: =H6-K6
A7: 3 | B7: Cayenne | C7: CHAR — parking visiteurs | D7: Pied double 2x22 kW | E7: FLT_ENT | F7: 4 | G7: 5670 | H7: =F7*G7 | I7: =IFERROR(VLOOKUP(E7,'Bareme ADVENIR'!$B$4:$E$13,2,FALSE),0) | J7: =IFERROR(VLOOKUP(E7,'Bareme ADVENIR'!$B$4:$E$13,3,FALSE),0) | K7: =MIN(I7*F7,H7*J7) | L7: =H7-K7
A8: 4 | B8: Kourou | C8: CSG — parking salaries | D8: Pied double 2x22 kW | E8: SAL_IND | F8: 6 | G8: 5670 | H8: =F8*G8 | I8: =IFERROR(VLOOKUP(E8,'Bareme ADVENIR'!$B$4:$E$13,2,FALSE),0) | J8: =IFERROR(VLOOKUP(E8,'Bareme ADVENIR'!$B$4:$E$13,3,FALSE),0) | K8: =MIN(I8*F8,H8*J8) | L8: =H8-K8
A9: 5 | B9: Kourou | C9: Front de mer — voirie | D9: Totem 3 departs (36 kVa) | E9: VOI_AC | F9: 2 | G9: 7100 | H9: =F9*G9 | I9: =IFERROR(VLOOKUP(E9,'Bareme ADVENIR'!$B$4:$E$13,2,FALSE),0) | J9: =IFERROR(VLOOKUP(E9,'Bareme ADVENIR'!$B$4:$E$13,3,FALSE),0) | K9: =MIN(I9*F9,H9*J9) | L9: =H9-K9
A10: 6 | B10: Saint-Laurent-du-Maroni | C10: Centre administratif | D10: Totem 3 departs (36 kVa) | E10: VOI_AC | F10: 3 | G10: 7100 | H10: =F10*G10 | I10: =IFERROR(VLOOKUP(E10,'Bareme ADVENIR'!$B$4:$E$13,2,FALSE),0) | J10: =IFERROR(VLOOKUP(E10,'Bareme ADVENIR'!$B$4:$E$13,3,FALSE),0) | K10: =MIN(I10*F10,H10*J10) | L10: =H10-K10
A11: 7 | B11: Saint-Laurent-du-Maroni | C11: Hopital — visiteurs | D11: Pied solo 1x22 kW | E11: POP_AC | F11: 3 | G11: 4200 | H11: =F11*G11 | I11: =IFERROR(VLOOKUP(E11,'Bareme ADVENIR'!$B$4:$E$13,2,FALSE),0) | J11: =IFERROR(VLOOKUP(E11,'Bareme ADVENIR'!$B$4:$E$13,3,FALSE),0) | K11: =MIN(I11*F11,H11*J11) | L11: =H11-K11
A12: 8 | B12: Matoury | C12: Centre commercial Family Plaza | D12: Pied double 2x22 kW | E12: POP_AC | F12: 4 | G12: 5670 | H12: =F12*G12 | I12: =IFERROR(VLOOKUP(E12,'Bareme ADVENIR'!$B$4:$E$13,2,FALSE),0) | J12: =IFERROR(VLOOKUP(E12,'Bareme ADVENIR'!$B$4:$E$13,3,FALSE),0) | K12: =MIN(I12*F12,H12*J12) | L12: =H12-K12
A13: 9 | B13: Macouria | C13: RN1 — aire de service | D13: Borne rapide DC 120 kW | E13: VOI_DC | F13: 2 | G13: 54500 | H13: =F13*G13 | I13: =IFERROR(VLOOKUP(E13,'Bareme ADVENIR'!$B$4:$E$13,2,FALSE),0) | J13: =IFERROR(VLOOKUP(E13,'Bareme ADVENIR'!$B$4:$E$13,3,FALSE),0) | K13: =MIN(I13*F13,H13*J13) | L13: =H13-K13
A14: 10 | B14: Remire-Montjoly | C14: Plage — parking communal | D14: Pied double 2x22 kW | E14: VOI_AC | F14: 4 | G14: 5670 | H14: =F14*G14 | I14: =IFERROR(VLOOKUP(E14,'Bareme ADVENIR'!$B$4:$E$13,2,FALSE),0) | J14: =IFERROR(VLOOKUP(E14,'Bareme ADVENIR'!$B$4:$E$13,3,FALSE),0) | K14: =MIN(I14*F14,H14*J14) | L14: =H14-K14
A15: 11 | B15: Mana | C15: Mairie | D15: Pied solo 1x22 kW | E15: VOI_AC | F15: 2 | G15: 4200 | H15: =F15*G15 | I15: =IFERROR(VLOOKUP(E15,'Bareme ADVENIR'!$B$4:$E$13,2,FALSE),0) | J15: =IFERROR(VLOOKUP(E15,'Bareme ADVENIR'!$B$4:$E$13,3,FALSE),0) | K15: =MIN(I15*F15,H15*J15) | L15: =H15-K15
A16: 12 | B16: Iracoubo | C16: Mairie | D16: Pied solo 1x22 kW | E16: VOI_AC | F16: 2 | G16: 4200 | H16: =F16*G16 | I16: =IFERROR(VLOOKUP(E16,'Bareme ADVENIR'!$B$4:$E$13,2,FALSE),0) | J16: =IFERROR(VLOOKUP(E16,'Bareme ADVENIR'!$B$4:$E$13,3,FALSE),0) | K16: =MIN(I16*F16,H16*J16) | L16: =H16-K16
... A19: 15 | B19: Macouria | C19: Residence collective La Rougerie | D19: WallBox murale 22 kW | E19: RES_COL | F19: 6 | G19: 1620 | H19: =F19*G19 | I19: =IFERROR(VLOOKUP(E19,'Bareme ADVENIR'!$B$4:$E$13,2,FALSE),0) | J19: =IFERROR(VLOOKUP(E19,'Bareme ADVENIR'!$B$4:$E$13,3,FALSE),0) | K19: =MIN(I19*F19,H19*J19) | L19: =H19-K19
A21: TOTAL | F21: =SUM(F5:F19) | H21: =SUM(H5:H19) | K21: =SUM(K5:K19) | L21: =SUM(L5:L19)
A24: INDICATEURS CLES
A26: Nb total de points de charge | C26: =F21
A27: Investissement total HT | C27: =H21
A28: Aide ADVENIR sollicitee | C28: =K21
A29: Taux moyen d'aide / investissement | C29: =K21/H21
A30: Reste a charge HT (autofinancement) | C30: =L21

Sheet Plan financement
A1: Plan de financement previsionnel — Phase 1
A3: Source | B3: Type | C3: Montant HT (€) | D3: Part (% du total)
A4: ADVENIR (subvention) | B4: Aide publique | C4: =Chiffrage!K21 | D4: =C4/SUM($C$4:$C$8)
A5: Apport associe(s) | B5: Fonds propres | C5: 30000 | D5: =C5/SUM($C$4:$C$8)
A6: Emprunt bancaire | B6: Dette | C6: 80000 | D6: =C6/SUM($C$4:$C$8)
A7: Subvention CTG / FEDER | B7: Aide regionale | C7: 20000 | D7: =C7/SUM($C$4:$C$8)
A8: Autofinancement (CAF) | B8: Tresorerie | C8: 0 | D8: =C8/SUM($C$4:$C$8)
A10: TOTAL | C10: =SUM(C4:C8) | D10: =SUM(D4:D8)
A12: Le total doit egaler l'investissement HT calcule en feuille 'Chiffrage'.
A13: Chiffrage feuille 2 — Investissement HT total : | C13: =Chiffrage!H21
A14: Plan financement total : | C14: =C10
A15: Ecart (doit etre 0) : | C15: =C13-C14
